market_research/__init__.py
market_research/analysis/__init__.py
market_research/analysis/_analysis_scheme.py
market_research/analysis/imgemanger.py
market_research/analysis/textmanager.py
market_research/ir/__init__.py
market_research/ir/calendar.py
market_research/ir/ir.py
market_research/ir/macro.py
market_research/ir/FinanceDataReader_mdify/__init__.py
market_research/ir/FinanceDataReader_mdify/_utils.py
market_research/ir/FinanceDataReader_mdify/back_chart.py
market_research/ir/FinanceDataReader_mdify/data.py
market_research/ir/FinanceDataReader_mdify/chart/__init__.py
market_research/ir/FinanceDataReader_mdify/chart/candle.py
market_research/ir/FinanceDataReader_mdify/chart/plot.py
market_research/ir/FinanceDataReader_mdify/ecos/__init__.py
market_research/ir/FinanceDataReader_mdify/ecos/data.py
market_research/ir/FinanceDataReader_mdify/ecos/snap.py
market_research/ir/FinanceDataReader_mdify/fred/__init__.py
market_research/ir/FinanceDataReader_mdify/fred/data.py
market_research/ir/FinanceDataReader_mdify/investing/__init__.py
market_research/ir/FinanceDataReader_mdify/investing/data.py
market_research/ir/FinanceDataReader_mdify/investing/listing.py
market_research/ir/FinanceDataReader_mdify/krx/__init__.py
market_research/ir/FinanceDataReader_mdify/krx/data.py
market_research/ir/FinanceDataReader_mdify/krx/listing.py
market_research/ir/FinanceDataReader_mdify/krx/snap.py
market_research/ir/FinanceDataReader_mdify/nasdaq/__init__.py
market_research/ir/FinanceDataReader_mdify/nasdaq/listing.py
market_research/ir/FinanceDataReader_mdify/naver/__init__.py
market_research/ir/FinanceDataReader_mdify/naver/data.py
market_research/ir/FinanceDataReader_mdify/naver/listing.py
market_research/ir/FinanceDataReader_mdify/naver/snap.py
market_research/ir/FinanceDataReader_mdify/wikipedia/__init__.py
market_research/ir/FinanceDataReader_mdify/wikipedia/listing.py
market_research/ir/FinanceDataReader_mdify/yahoo/__init__.py
mkt_retv-1.638.dist-info/METADATA
mkt_retv-1.638.dist-info/WHEEL
mkt_retv-1.638.dist-info/entry_points.txt
mkt_retv-1.638.dist-info/top_level.txt
mkt_retv-1.638.dist-info/RECORD
