Metadata-Version: 2.1
Name: mkt-retv
Version: 1.638
Summary: market research TV 
Home-page: https://github.com/xikest/research_market_tv
Author: xikest
Project-URL: Source, https://github.com/xikest/research_market_tv
Project-URL: Bug Tracker, https://github.com/xikest/research_market_tv/issues
Requires-Python: >=3.7
Requires-Dist: numpy
Requires-Dist: pandas
Requires-Dist: selenium
Requires-Dist: beautifulsoup4
Requires-Dist: requests
Requires-Dist: tqdm
Requires-Dist: openpyxl
Requires-Dist: wordcloud
Requires-Dist: nltk
Requires-Dist: scikit-learn
Requires-Dist: openai
Requires-Dist: matplotlib
Requires-Dist: seaborn
Requires-Dist: plotly
